commands.py
dropbox_pi_cli-0.0.5.dist-info/LICENSE
dropbox_pi_cli-0.0.5.dist-info/METADATA
dropbox_pi_cli-0.0.5.dist-info/WHEEL
dropbox_pi_cli-0.0.5.dist-info/entry_points.txt
dropbox_pi_cli-0.0.5.dist-info/top_level.txt
dropbox_pi_cli-0.0.5.dist-info/RECORD
